flashlab-1.3.2.dist-info/METADATA
flashlab-1.3.2.dist-info/WHEEL
flashlab-1.3.2.dist-info/entry_points.txt
flashlab-1.3.2.dist-info/licenses/LICENSE
flashlab/__init__.py
flashlab/__main__.py
flashlab/flashcode.py
flashlab/flashcode_mapping.py
flashlab/flashlab.py
flashlab/flashlab_qt6.py
flashlab/flashlab_shell.py
flashlab/options.json
flashlab-1.3.2.dist-info/RECORD
