Metadata-Version: 2.1
Name: flashlab
Version: 1.3.2
Summary: A simple tool to help creating and editing Motorola APX FLASHcodes
Author-Email: k4yt3x <i@k4yt3x.com>
License: ISC
Requires-Python: >=3.8
Requires-Dist: PyQt6>=6.6.1
